pyrdsbackup/__init__.py
pyrdsbackup/db/__init__.py
pyrdsbackup/db/test.py
pyrdsbackup/db/mssql/__init__.py
pyrdsbackup/db/mssql/mssql.py
pyrdsbackup-1.1.2.dist-info/METADATA
pyrdsbackup-1.1.2.dist-info/RECORD
pyrdsbackup-1.1.2.dist-info/WHEEL
pyrdsbackup-1.1.2.dist-info/top_level.txt
