Metadata-Version: 2.1
Name: pyrdsbackup
Version: 1.1.2
Summary: Simplify RDS Backups to S3
Home-page: https://github.com/darmagedon/pyrds-backup.git
Author: Sparsha Dotel
Author-email: sparshadotel@gmail.com
License: UNKNOWN
Keywords: cli
Platform: UNKNOWN
Classifier: Programming Language :: Python :: 2
Classifier: Programming Language :: Python :: 3
Classifier: License :: OSI Approved :: GNU Affero General Public License v3
Classifier: Operating System :: OS Independent
Requires-Dist: pyodbc (==4.0.23)
